pyfreebody/__init__.py
pyfreebody/core.py
pyfreebody-0.4.2.dist-info/LICENSE
pyfreebody-0.4.2.dist-info/METADATA
pyfreebody-0.4.2.dist-info/WHEEL
pyfreebody-0.4.2.dist-info/top_level.txt
pyfreebody-0.4.2.dist-info/RECORD
