Metadata-Version: 2.1
Name: pyfreebody
Version: 0.4.2
Summary: A package for generating freebody diagrams.
Home-page: https://github.com/velocitatem/pyfreebody
Author: Daniel Rosel
Author-email: daniel@alves.world
License-File: LICENSE
Requires-Dist: Pillow ==10.4.0
